{
    "cli": true,
    "target": "directory",
    "adapterName": "botslab360",
    "title": "Botslab 360",
    "description": "Adapter for Botslab 360 Vacuum",
    "keywords": ["360", "Vacuum", "botslab"],
    "expert": "yes",
    "features": ["adapter"],
    "adminFeatures": [],
    "type": "household",
    "startMode": "daemon",
    "connectionType": "cloud",
    "dataSource": "poll",
    "connectionIndicator": "yes",
    "language": "JavaScript",
    "nodeVersion": "14",
    "adminUi": "json",
    "tools": ["ESLint", "type checking", "Prettier"],
    "releaseScript": "no",
    "devServer": "no",
    "indentation": "Space (4)",
    "quotes": "double",
    "es6class": "yes",
    "authorName": "TA2k",
    "authorGithub": "TA2k",
    "authorEmail": "tombox2020@gmail.com",
    "gitRemoteProtocol": "HTTPS",
    "gitCommit": "no",
    "defaultBranch": "main",
    "license": "MIT License",
    "dependabot": "no",
    "creatorVersion": "2.3.0"
}
